dagstermill/__init__.py
dagstermill/__main__.py
dagstermill/cli.py
dagstermill/compat.py
dagstermill/context.py
dagstermill/engine.py
dagstermill/errors.py
dagstermill/factory.py
dagstermill/io_managers.py
dagstermill/manager.py
dagstermill/serialize.py
dagstermill/translator.py
dagstermill/version.py
dagstermill/examples/__init__.py
dagstermill/examples/repository.py
dagstermill-1.0.5.dist-info/LICENSE
dagstermill-1.0.5.dist-info/METADATA
dagstermill-1.0.5.dist-info/WHEEL
dagstermill-1.0.5.dist-info/entry_points.txt
dagstermill-1.0.5.dist-info/top_level.txt
dagstermill-1.0.5.dist-info/RECORD
