Metadata-Version: 2.1
Name: dagstermill
Version: 1.0.5
Summary: run notebooks using the Dagster tools
Home-page: UNKNOWN
Author: Elementl
Author-email: hello@elementl.com
License: Apache-2.0
Platform: UNKNOWN
Classifier: Programming Language :: Python :: 3.7
Classifier: Programming Language :: Python :: 3.8
Classifier: Programming Language :: Python :: 3.9
Classifier: Programming Language :: Python :: 3.10
Classifier: License :: OSI Approved :: Apache Software License
Classifier: Operating System :: OS Independent
License-File: LICENSE
Requires-Dist: dagster (==1.0.5)
Requires-Dist: ipykernel (!=5.4.0,!=5.4.1,>=4.9.0)
Requires-Dist: ipython-genutils (>=0.2.0)
Requires-Dist: packaging (>=20.5)
Requires-Dist: papermill (>=1.0.0)
Requires-Dist: scrapbook (>=0.5.0)
Provides-Extra: test
Requires-Dist: matplotlib ; extra == 'test'
Requires-Dist: nbconvert ; extra == 'test'
Requires-Dist: scikit-learn (>=0.19.0) ; extra == 'test'
Requires-Dist: tqdm (<=4.48) ; extra == 'test'
